generatorLibCommonsPython3/.gitignore
generatorLibCommonsPython3/__init__.py
generatorLibCommonsPython3/client/.gitignore
generatorLibCommonsPython3/client/__init__.py
generatorLibCommonsPython3/client/exception/.gitignore
generatorLibCommonsPython3/client/exception/__init__.py
generatorLibCommonsPython3/client/exception/request/.gitignore
generatorLibCommonsPython3/client/exception/request/__init__.py
generatorLibCommonsPython3/client/exception/request/nova_api_client_request_exception.py
generatorLibCommonsPython3/client/exception/response/.gitignore
generatorLibCommonsPython3/client/exception/response/__init__.py
generatorLibCommonsPython3/client/exception/response/nova_api_client_response_exception.py
generatorLibCommonsPython3/client/exception/response/nova_api_client_response_timeout_exception.py
generatorLibCommonsPython3/client/request/.gitignore
generatorLibCommonsPython3/client/request/__init__.py
generatorLibCommonsPython3/client/request/nova_request_config.py
generatorLibCommonsPython3/exception/.gitignore
generatorLibCommonsPython3/exception/__init__.py
generatorLibCommonsPython3/exception/error_message.py
generatorLibCommonsPython3/exception/error_message_params.py
generatorLibCommonsPython3/exception/error_message_type.py
generatorLibCommonsPython3/exception/errors.py
generatorLibCommonsPython3/exception/igenerated_exception.py
generatorLibCommonsPython3/metadata/.gitignore
generatorLibCommonsPython3/metadata/__init__.py
generatorLibCommonsPython3/metadata/nova_medatadata.py
generatorLibCommonsPython3/metadata/nova_metadata.py
generatorLibCommonsPython3/metadata/headers/.gitignore
generatorLibCommonsPython3/metadata/headers/__init__.py
generatorLibCommonsPython3/metadata/headers/nova_implicit_headers_input.py
generatorLibCommonsPython3/metadata/headers/nova_implicit_headers_output.py
generatorLibCommonsPython3/random/.gitignore
generatorLibCommonsPython3/random/__init__.py
generatorLibCommonsPython3/random/random_utils.py
generatorLibCommonsPython3-1.0.5.dist-info/.gitignore
generatorLibCommonsPython3-1.0.5.dist-info/METADATA
generatorLibCommonsPython3-1.0.5.dist-info/WHEEL
generatorLibCommonsPython3-1.0.5.dist-info/top_level.txt
generatorLibCommonsPython3-1.0.5.dist-info/RECORD
