Metadata-Version: 2.1
Name: generatorLibCommonsPython3
Version: 1.0.5
Summary: Common utilities for autogenerated projects using APIRestGenerator and Python 3
Home-page: https://sites.google.com/a/bbva.com/low-latency/architecture-utilities/apirestgenerator
Author: Low Latency
Author-email: lowlatency-architecture-support@bbva.com
License: MIT License
Platform: UNKNOWN
Classifier: Development Status :: 3 - Alpha
Classifier: License :: OSI Approved :: MIT License
Classifier: Intended Audience :: Developers
Classifier: Natural Language :: English
Classifier: Operating System :: OS Independent
Classifier: Programming Language :: Python
Classifier: Programming Language :: Python :: 3
Classifier: Programming Language :: Python :: 3.7
Classifier: Topic :: Software Development :: Libraries
Classifier: Topic :: Software Development :: Libraries :: Python Modules
